{
"type": "FeatureCollection",
"name": "point_GEOJSON",
"crs": { "type": "name", "properties": { "name": "urn:ogc:def:crs:OGC:1.3:CRS84" } },
"features": [
{ "type": "Feature", "properties": { "id": 1, "name": "well" }, "geometry": { "type": "Point", "coordinates": [ -79.051233740695949, 35.912079654653304 ] } },
{ "type": "Feature", "properties": { "id": 2, "name": "poplartree" }, "geometry": { "type": "Point", "coordinates": [ -79.051670334314167, 35.912857183712056 ] } },
{ "type": "Feature", "properties": { "id": 3, "name": "arboretum" }, "geometry": { "type": "Point", "coordinates": [ -79.048935666214589, 35.913773858242564 ] } }
]
}
